jgt_common/__init__.py
jgt_common/assert_.py
jgt_common/check.py
jgt_common/futures.py
jgt_common/http_helpers.py
jgt_common/tag_to_url.py
jgt_common/uuid_replacer.py
jgt_common-1.1.1.dist-info/entry_points.txt
jgt_common-1.1.1.dist-info/WHEEL
jgt_common-1.1.1.dist-info/METADATA
jgt_common-1.1.1.dist-info/RECORD
